setup.cfg
setup.py
pyxe/__init__.py
pyxe/area_analysis.py
pyxe/edi12_analysis.py
pyxe/fitting_functions.py
pyxe/fitting_tools.py
pyxe/merge.py
pyxe/merge_tools.py
pyxe/plotting.py
pyxe/plotting_tools.py
pyxe/reload.py
pyxe/strain_tools.py
pyxe.egg-info/PKG-INFO
pyxe.egg-info/SOURCES.txt
pyxe.egg-info/dependency_links.txt
pyxe.egg-info/top_level.txt