Metadata-Version: 1.1
Name: pyxe
Version: 0.7.1
Summary: XRD strain analysis package. Efficient analysis and visulisation of diffraction data.
Home-page: https://github.com/casimp/pyxe
Author: C. Simpson
Author-email: c.a.simpson01@gmail.com
License: LICENSE.txt
Download-URL: https://github.com/casimp/pyxe/tarball/v0.7.1
Keywords: XRD,EDXD,x-ray,diffraction,strain,synchrotron
Platform: UNKNOWN
Classifier: Development Status :: 3 - Alpha
Classifier: License :: OSI Approved :: MIT License
Classifier: Programming Language :: Python :: 2.7
Classifier: Programming Language :: Python :: 3.4
Classifier: Programming Language :: Python :: 3.5
Classifier: Operating System :: MacOS :: MacOS X
Classifier: Operating System :: Microsoft :: Windows
